crispr_shrinkage/__init__.py
crispr_shrinkage/framework/CrisprShrinkage.py
crispr_shrinkage/framework/CrisprShrinkageVisualization.py
crispr_shrinkage-0.1.71.dist-info/METADATA
crispr_shrinkage-0.1.71.dist-info/WHEEL
crispr_shrinkage-0.1.71.dist-info/RECORD
