Metadata-Version: 2.1
Name: crispr-shrinkage
Version: 0.1.71
Summary: 
Author: Basheer Becerra
Author-email: bbecerra@fas.harvard.edu
Requires-Python: >=3.8,<3.12
Classifier: Programming Language :: Python :: 3
Classifier: Programming Language :: Python :: 3.8
Classifier: Programming Language :: Python :: 3.9
Classifier: Programming Language :: Python :: 3.10
Classifier: Programming Language :: Python :: 3.11
Requires-Dist: matplotlib (>=3.6.3,<4.0.0)
Requires-Dist: numpy (>=1.24.1,<2.0.0)
Requires-Dist: scipy (>=1.10.0,<2.0.0)
